{
  "project_info": {
    "project_number": "672852906704",
    "project_id": "picknick-6c765",
    "storage_bucket": "picknick-6c765.firebasestorage.app"
  },
  "client": [
    {
      "client_info": {
        "mobilesdk_app_id": "1:672852906704:android:8f06cbea226fc95b7084d5",
        "android_client_info": {
          "package_name": "com.nickpick"
        }
      },
      "oauth_client": [],
      "api_key": [
        {
          "current_key": "AIzaSyCeIepiYpDGVhfckfNSJRTs8EoyawOHtEw"
        }
      ],
      "services": {
        "appinvite_service": {
          "other_platform_oauth_client": []
        }
      }
    }
  ],
  "configuration_version": "1"
}